[
  {
    "id": "adv_e_009",
    "num": 1,
    "type": "quad_eq",
    "domain": "advanced_math",
    "difficulty": "easy",
    "calcAgnostic": true,
    "context": "2x² − 8 = 0",
    "stimulus": null,
    "table": null,
    "question": "What is the positive value of x that satisfies the given equation?",
    "choices": {
      "A": "1",
      "B": "2",
      "C": "4",
      "D": "8"
    },
    "answer": "B",
    "isSPR": false,
    "explanation": "2x² = 8 → x² = 4 → x = ±2. The positive value is 2. Choice C (4) results from dividing 8 by 2 but forgetting to take the square root. Choice D (8) is the constant on the right-hand side, not the solution. Choice A (1) has no clear derivation from this equation."
  },
  {
    "id": "adv_e_010",
    "num": 2,
    "type": "exp_func_interp",
    "domain": "advanced_math",
    "difficulty": "easy",
    "calcAgnostic": false,
    "context": "The function f(n) = 500 · 2^n gives the number of views a video has received n days after it was posted.",
    "stimulus": null,
    "table": null,
    "question": "Which of the following is the best interpretation of 'f(4) = 8,000' in this context?",
    "choices": {
      "A": "Four days after posting, the video has received 8,000 views.",
      "B": "The video receives 8,000 new views every 4 days.",
      "C": "The video received 8,000 views on the day it was posted.",
      "D": "After 8,000 days, the video has received 4 views."
    },
    "answer": "A",
    "isSPR": false,
    "explanation": "n = 4 is the input (number of days), and f(4) = 8,000 is the output (total views). So four days after posting, the video has 8,000 views. Choice B misidentifies f(4) as a rate of new views per day rather than a total. Choice C incorrectly identifies f(0) = 500 with f(4) = 8,000. Choice D swaps the roles of input and output."
  },
  {
    "id": "adv_e_011",
    "num": 3,
    "type": "exponent_rules",
    "domain": "advanced_math",
    "difficulty": "easy",
    "calcAgnostic": true,
    "context": null,
    "stimulus": null,
    "table": null,
    "question": "Which expression is equivalent to \\(\\dfrac{x^{12}}{x^4}\\)?",
    "choices": {
      "A": "\\(x^8\\)",
      "B": "\\(x^3\\)",
      "C": "\\(x^{48}\\)",
      "D": "\\(x^{16}\\)"
    },
    "answer": "A",
    "isSPR": false,
    "explanation": "When dividing expressions with the same base, subtract the exponents: \\(x^{12}/x^4 = x^{12-4} = x^8\\). Choice B results from dividing the exponents (12 ÷ 4 = 3) instead of subtracting. Choice C multiplies the exponents (12 × 4 = 48) instead of subtracting. Choice D adds the exponents (12 + 4 = 16) instead of subtracting."
  },
  {
    "id": "adv_e_012",
    "num": 4,
    "type": "func_transform_eval",
    "domain": "advanced_math",
    "difficulty": "easy",
    "calcAgnostic": true,
    "context": "The function g is defined by g(x) = f(x) − 6. The value of f(5) is 14.",
    "stimulus": null,
    "table": null,
    "question": "What is the value of g(5)?",
    "choices": null,
    "answer": "8",
    "isSPR": true,
    "explanation": "g(5) = f(5) − 6 = 14 − 6 = 8. Valid entry: 8."
  },
  {
    "id": "adv_e_013",
    "num": 5,
    "type": "alg_manipulation",
    "domain": "advanced_math",
    "difficulty": "easy",
    "calcAgnostic": true,
    "context": "5(k + 2j) = 3k + 20",
    "stimulus": null,
    "table": null,
    "question": "Which equation correctly expresses k in terms of j?",
    "choices": {
      "A": "k = 10 − 5j",
      "B": "k = 10 + 5j",
      "C": "k = 5j − 10",
      "D": "k = 20 − 10j"
    },
    "answer": "A",
    "isSPR": false,
    "explanation": "Expand the left side: 5k + 10j = 3k + 20. Subtract 3k and subtract 10j: 2k = 20 − 10j. Divide by 2: k = 10 − 5j. Choice B has the wrong sign on 5j. Choice C negates the entire result. Choice D is 2k rather than k — the student forgot to divide by 2."
  },
  {
    "id": "adv_e_014",
    "num": 6,
    "type": "exp_func_model",
    "domain": "advanced_math",
    "difficulty": "easy",
    "calcAgnostic": false,
    "context": "A bank account earns 3% annual interest, compounding annually. The initial balance is $2,000.",
    "stimulus": null,
    "table": null,
    "question": "Which function gives the balance B(t), in dollars, after t years?",
    "choices": {
      "A": "B(t) = 2000 · (1.03)^t",
      "B": "B(t) = 2000 · (0.03)^t",
      "C": "B(t) = 2000 + 0.03t",
      "D": "B(t) = 2000 · (1.3)^t"
    },
    "answer": "A",
    "isSPR": false,
    "explanation": "Annual compounding at 3% means each year's balance is multiplied by 1.03: B(t) = 2000 · (1.03)^t. Choice B uses 0.03 as the base, which would collapse the account to near zero rapidly (decay rather than growth). Choice C models linear growth, adding a fixed dollar amount each year rather than multiplying by a factor. Choice D uses 1.3, representing 30% annual growth rather than 3%."
  },
  {
    "id": "adv_e_015",
    "num": 7,
    "type": "quad_eq",
    "domain": "advanced_math",
    "difficulty": "easy",
    "calcAgnostic": true,
    "context": "x² + 6x + 5 = 0",
    "stimulus": null,
    "table": null,
    "question": "What are the solutions to the given equation?",
    "choices": {
      "A": "x = −5 and x = −1",
      "B": "x = 5 and x = 1",
      "C": "x = −5 and x = 1",
      "D": "x = 5 and x = −1"
    },
    "answer": "A",
    "isSPR": false,
    "explanation": "Factor: (x + 5)(x + 1) = 0. Solutions: x = −5 or x = −1. Verify: (−5)² + 6(−5) + 5 = 25 − 30 + 5 = 0 ✓; (−1)² + 6(−1) + 5 = 1 − 6 + 5 = 0 ✓. Choice B gives the positives of the correct roots. Choice C mixes signs. Choice D reverses the signs on each root."
  },
  {
    "id": "adv_e_016",
    "num": 8,
    "type": "exp_func_interp",
    "domain": "advanced_math",
    "difficulty": "easy",
    "calcAgnostic": true,
    "context": "The function f(t) = 800 · (0.75)^t gives the estimated number of fish in a pond t years after fishing restrictions were lifted.",
    "stimulus": null,
    "table": null,
    "question": "What is the best interpretation of 800 in this context?",
    "choices": {
      "A": "The fish population decreases by 800 each year.",
      "B": "There were 800 fish in the pond when the restrictions were lifted.",
      "C": "After 800 years, approximately 0.75 fish remain.",
      "D": "The pond's fish population grew by a factor of 800."
    },
    "answer": "B",
    "isSPR": false,
    "explanation": "800 is f(0), the population when t = 0 — when the restrictions were lifted. Choice A describes a linear decrease of 800 per year, not the exponential behavior here. Choice C inverts input and output. Choice D misidentifies 800 as a multiplicative growth factor rather than an initial population count."
  },
  {
    "id": "adv_m_013",
    "num": 9,
    "type": "quad_func_build",
    "domain": "advanced_math",
    "difficulty": "medium",
    "calcAgnostic": false,
    "context": "A square has side length s inches. A second square has a perimeter that is 20 inches greater than that of the first square.",
    "stimulus": null,
    "table": null,
    "question": "Which function gives the area of the second square, in square inches?",
    "choices": {
      "A": "(s + 5)²",
      "B": "(s + 20)²",
      "C": "s² + 20",
      "D": "4s² + 20"
    },
    "answer": "A",
    "isSPR": false,
    "explanation": "First square: perimeter = 4s. Second square: perimeter = 4s + 20, so side length = (4s + 20)/4 = s + 5. Area = (s + 5)². Choice B adds the full perimeter difference (20) to the side rather than dividing by 4 first. Choice C adds 20 directly to the area, ignoring the relationship between perimeter and side length. Choice D multiplies the area by 4 (confusing the area scale factor with the perimeter relationship)."
  },
  {
    "id": "adv_m_014",
    "num": 10,
    "type": "exp_func_interp",
    "domain": "advanced_math",
    "difficulty": "medium",
    "calcAgnostic": false,
    "context": "The function P(d) = 120 · (1.08)^d gives the estimated number of social media followers an account has d days after launching a promotional campaign.",
    "stimulus": null,
    "table": null,
    "question": "Which of the following is the best interpretation of the statement 'P(7) is approximately equal to 206' in this context?",
    "choices": {
      "A": "Seven days after launching the campaign, the account has approximately 206 followers.",
      "B": "The account gains approximately 206 followers every 7 days during the campaign.",
      "C": "Before the campaign launched, the account had approximately 206 followers.",
      "D": "After 206 days, the account has approximately 7 followers."
    },
    "answer": "A",
    "isSPR": false,
    "explanation": "d = 7 is the number of days elapsed, and P(7) ≈ 206 is the total followers at that time. Choice B misreads P(7) as a rate (new followers every 7 days) rather than a total. Choice C identifies P(0) = 120 as the pre-campaign count, not 206. Choice D swaps the roles of input and output."
  },
  {
    "id": "adv_m_015",
    "num": 11,
    "type": "alg_manipulation",
    "domain": "advanced_math",
    "difficulty": "medium",
    "calcAgnostic": true,
    "context": "\\(\\dfrac{x}{y} - 3 = z\\)",
    "stimulus": null,
    "table": null,
    "question": "Which equation correctly expresses x in terms of y and z?",
    "choices": {
      "A": "x = y(z + 3)",
      "B": "x = y + z + 3",
      "C": "x = z/y + 3",
      "D": "x = y + z − 3"
    },
    "answer": "A",
    "isSPR": false,
    "explanation": "Add 3 to both sides: x/y = z + 3. Multiply both sides by y: x = y(z + 3). Choice B adds y instead of multiplying by it. Choice C divides z by y instead of multiplying y by the entire expression (z + 3). Choice D adds y to the expression rather than multiplying."
  },
  {
    "id": "adv_m_016",
    "num": 12,
    "type": "discriminant_count",
    "domain": "advanced_math",
    "difficulty": "medium",
    "calcAgnostic": true,
    "context": "4x² − 12x + 9 = 0",
    "stimulus": null,
    "table": null,
    "question": "How many distinct real solutions does the given equation have?",
    "choices": {
      "A": "0",
      "B": "1",
      "C": "2",
      "D": "4"
    },
    "answer": "B",
    "isSPR": false,
    "explanation": "Discriminant = b² − 4ac = (−12)² − 4(4)(9) = 144 − 144 = 0. A discriminant of exactly zero means there is one distinct real solution (a repeated root). The equation factors as (2x − 3)² = 0, confirming the single solution x = 3/2. Choice A (0) would require a negative discriminant. Choice C (2) would require a positive discriminant. Choice D (4) exceeds the maximum number of solutions for any quadratic."
  },
  {
    "id": "adv_m_017",
    "num": 13,
    "type": "quadratic_formula_k",
    "domain": "advanced_math",
    "difficulty": "medium",
    "calcAgnostic": false,
    "context": "2x² + 6x − 1 = 0\nOne solution to the given equation can be written as x = (−6 + √k) / 4, where k is a positive constant.",
    "stimulus": null,
    "table": null,
    "question": "What is the value of k?",
    "choices": null,
    "answer": "44",
    "isSPR": true,
    "explanation": "Using the quadratic formula with a = 2, b = 6, c = −1: x = (−6 ± √(b² − 4ac)) / (2a) = (−6 ± √(36 + 8)) / 4 = (−6 ± √44) / 4. So k = 44. Valid entry: 44."
  },
  {
    "id": "adv_m_018",
    "num": 14,
    "type": "func_transform_eval",
    "domain": "advanced_math",
    "difficulty": "medium",
    "calcAgnostic": true,
    "context": "The graph of y = f(x) + 7 passes through the point (−3, 2).",
    "stimulus": null,
    "table": null,
    "question": "What is the value of f(−3)?",
    "choices": null,
    "answer": "-5",
    "isSPR": true,
    "explanation": "Substitute (−3, 2) into y = f(x) + 7: 2 = f(−3) + 7 → f(−3) = −5. The trap is entering 9 (adding 7 to 2 rather than subtracting). Valid entries: -5."
  },
  {
    "id": "adv_m_019",
    "num": 15,
    "type": "exp_model_table",
    "domain": "advanced_math",
    "difficulty": "medium",
    "calcAgnostic": false,
    "context": null,
    "stimulus": null,
    "table": "| x | y |\n|---|---|\n| 0 | 81 |\n| 1 | 27 |\n| 2 | 9 |",
    "question": "The table shows three values of x and their corresponding values of y. Which equation defines y in terms of x?",
    "choices": {
      "A": "\\(y = 81 \\cdot \\left(\\frac{1}{3}\\right)^x\\)",
      "B": "\\(y = \\frac{1}{3} \\cdot 81^x\\)",
      "C": "y = 81 − 3x",
      "D": "\\(y = 81 \\cdot 3^x\\)"
    },
    "answer": "A",
    "isSPR": false,
    "explanation": "At x = 0, y = 81, so the initial value is 81. The ratio between consecutive y-values: 27/81 = 1/3 and 9/27 = 1/3. The common ratio is 1/3, giving y = 81 · (1/3)^x. Verify: y(0) = 81 ✓, y(1) = 27 ✓. Choice B swaps the initial value and the base. Choice C models linear decrease: y(1) = 78 ≠ 27. Choice D uses a growth factor of 3 instead of decay factor 1/3: y(1) = 243 ≠ 27."
  },
  {
    "id": "adv_m_020",
    "num": 16,
    "type": "exponent_rules",
    "domain": "advanced_math",
    "difficulty": "medium",
    "calcAgnostic": true,
    "context": null,
    "stimulus": null,
    "table": null,
    "question": "Which expression is equivalent to \\(x^{3/2}\\)?",
    "choices": {
      "A": "\\(\\sqrt{x^3}\\)",
      "B": "\\(\\frac{x^3}{2}\\)",
      "C": "\\(\\sqrt{3x}\\)",
      "D": "\\(3\\sqrt{x}\\)"
    },
    "answer": "A",
    "isSPR": false,
    "explanation": "\\(x^{3/2} = x^{3 \\cdot (1/2)} = (x^3)^{1/2} = \\sqrt{x^3}\\). Choice B interprets 3/2 as the fraction 'x³ divided by 2' rather than the exponent 3/2. Choice C misplaces the 3 inside the square root as a coefficient of x: \\(\\sqrt{3x} = (3x)^{1/2} \\neq x^{3/2}\\). Choice D treats x^(3/2) as 3 times x^(1/2): \\(3\\sqrt{x} = 3x^{1/2} \\neq x^{3/2}\\)."
  },
  {
    "id": "adv_m_021",
    "num": 17,
    "type": "no_solution_param",
    "domain": "advanced_math",
    "difficulty": "medium",
    "calcAgnostic": true,
    "context": "m(x + 2) = 4x + 2m + 3",
    "stimulus": null,
    "table": null,
    "question": "For what value of m does the given equation have no solution?",
    "choices": {
      "A": "−4",
      "B": "0",
      "C": "4",
      "D": "8"
    },
    "answer": "C",
    "isSPR": false,
    "explanation": "Expand the left side: mx + 2m = 4x + 2m + 3. Subtract 2m from both sides: mx = 4x + 3. Rearrange: (m − 4)x = 3. For no solution: the coefficient of x must be zero while the constant is nonzero: m − 4 = 0 → m = 4, giving 0 = 3, a contradiction ✓. Choice A (−4): (−4 − 4)x = 3 → −8x = 3 → x = −3/8. One solution. Choice B (0): −4x = 3 → x = −3/4. One solution. Choice D (8): 4x = 3 → x = 3/4. One solution."
  },
  {
    "id": "adv_m_022",
    "num": 18,
    "type": "system_nonlinear",
    "domain": "advanced_math",
    "difficulty": "medium",
    "calcAgnostic": false,
    "context": "y = 3x\ny = x² + 2x",
    "stimulus": null,
    "table": null,
    "question": "At which of the following points do the graphs of the equations in the given system intersect in the xy-plane?",
    "choices": {
      "A": "(0, 0) and (1, 3)",
      "B": "(0, 0) and (−1, −3)",
      "C": "(1, 3) only",
      "D": "(3, 9) and (0, 0)"
    },
    "answer": "A",
    "isSPR": false,
    "explanation": "Substitute y = 3x into y = x² + 2x: 3x = x² + 2x → x² − x = 0 → x(x − 1) = 0 → x = 0 or x = 1. At x = 0: y = 0. At x = 1: y = 3. Intersection points: (0, 0) and (1, 3). Choice B gives (−1, −3): x = −1 would require x(x−1) = 0, giving x = 0 or x = 1, not −1. Choice C omits the (0, 0) intersection. Choice D (3, 9): at x = 3, y = 9 on y = 3x, but y = 9 + 6 = 15 ≠ 9 on y = x² + 2x."
  },
  {
    "id": "adv_m_023",
    "num": 19,
    "type": "exp_func_model",
    "domain": "advanced_math",
    "difficulty": "medium",
    "calcAgnostic": false,
    "context": "The number of users of a new app is growing by 12% each week. There were 300 users in week 0.",
    "stimulus": null,
    "table": null,
    "question": "Which function models the number of users U(w) after w weeks?",
    "choices": {
      "A": "U(w) = 300 · (1.12)^w",
      "B": "U(w) = 300 · (0.12)^w",
      "C": "U(w) = 300 · (1.12) · w",
      "D": "U(w) = 300 + 12w"
    },
    "answer": "A",
    "isSPR": false,
    "explanation": "A 12% weekly growth means each week's count is multiplied by 1.12: U(w) = 300 · (1.12)^w. Choice B uses 0.12 as the base, producing a rapidly shrinking count. Choice C multiplies by 1.12 as a flat factor of w — linear, not exponential: U(2) = 300 · 1.12 · 2 = 672, not 300 · 1.12² = 376.3. Choice D models adding 12 users each week rather than growing by 12%."
  },
  {
    "id": "adv_m_024",
    "num": 20,
    "type": "exp_growth_period",
    "domain": "advanced_math",
    "difficulty": "medium",
    "calcAgnostic": false,
    "context": "A colony of mold doubles in size every 3 days. The colony initially covers 5 square centimeters.",
    "stimulus": null,
    "table": null,
    "question": "How many square centimeters does the colony cover after 12 days?",
    "choices": null,
    "answer": "80",
    "isSPR": true,
    "explanation": "12 days is exactly 12/3 = 4 doubling periods. Area = 5 × 2⁴ = 5 × 16 = 80. Traps: using 2^12 = 4,096 (confusing the number of days with the exponent) or 5 × 2 × 4 = 40 (multiplying linearly instead of exponentially). Valid entry: 80."
  },
  {
    "id": "adv_h_009",
    "num": 21,
    "type": "polynomial_factor",
    "domain": "advanced_math",
    "difficulty": "hard",
    "calcAgnostic": true,
    "context": null,
    "stimulus": null,
    "table": null,
    "question": "The expression \\(3x^2 + bx - 35\\), where b is a constant, can be written as \\((3x + k)(x + j)\\), where k and j are integer constants. Which of the following must be an integer?",
    "choices": {
      "A": "\\(b/3\\)",
      "B": "\\(b/k\\)",
      "C": "\\(35/3\\)",
      "D": "\\(35/k\\)"
    },
    "answer": "D",
    "isSPR": false,
    "explanation": "Expanding (3x + k)(x + j) = 3x² + (3j + k)x + kj. Matching coefficients: the leading coefficient is 3, b = 3j + k, and kj = −35. Since k and j are integers with kj = −35, the integer j equals −35/k, which means 35/k = −j must be an integer. Choice C: 35/3 ≈ 11.67, which is never an integer regardless of k or j. Choice A: b/3 = (3j + k)/3 = j + k/3. If k = 2 (not a divisor of 35), this is not an integer — but wait, k must divide −35, so valid k values are ±1, ±5, ±7, ±35. For k = 7: b/3 = j + 7/3, not an integer. Choice B: b/k = (3j + k)/k = 3j/k + 1 = 3(−35/k²) + 1 = −105/k² + 1. For k = 7: −105/49 + 1 ≈ −1.14. Not always an integer."
  },
  {
    "id": "adv_h_010",
    "num": 22,
    "type": "parabola",
    "domain": "advanced_math",
    "difficulty": "hard",
    "calcAgnostic": false,
    "context": null,
    "stimulus": null,
    "table": null,
    "question": "In the xy-plane, a parabola has vertex (−2, −6) and intersects the x-axis at two points. If the equation of the parabola is written in the form y = ax² + bx + c, which of the following could be the value of a + b + c?",
    "choices": {
      "A": "−10",
      "B": "−7",
      "C": "−6",
      "D": "−3"
    },
    "answer": "D",
    "isSPR": false,
    "explanation": "Since a + b + c = f(1), write the parabola in vertex form: y = a(x + 2)² − 6. At x = 1: f(1) = a(3)² − 6 = 9a − 6. For the parabola to intersect the x-axis at two points with the vertex below the x-axis (y = −6 < 0), the parabola must open upward: a > 0. So f(1) = 9a − 6 > −6. Only Choice D (−3) satisfies this: 9a − 6 = −3 → a = 1/3 > 0 ✓. Choices A (−10) and B (−7) require a < 0 — the parabola would open downward, with its highest point at y = −6 < 0 — no x-intercepts possible. Choice C (−6) requires a = 0, meaning no parabola exists."
  },
  {
    "id": "adv_h_011",
    "num": 23,
    "type": "quad_systems",
    "domain": "advanced_math",
    "difficulty": "hard",
    "calcAgnostic": false,
    "context": "y = x² + 2x + 6\ny = 4x + a\nIn the given system of equations, a is a constant. The graphs of the equations intersect at exactly one point (x, y) in the xy-plane.",
    "stimulus": null,
    "table": null,
    "question": "What is the value of x?",
    "choices": {
      "A": "−2",
      "B": "1",
      "C": "5",
      "D": "9"
    },
    "answer": "B",
    "isSPR": false,
    "explanation": "Substitute y = 4x + a into y = x² + 2x + 6: 4x + a = x² + 2x + 6 → x² − 2x + (6 − a) = 0. For exactly one intersection, the discriminant equals zero: (−2)² − 4(6 − a) = 0 → 4 − 24 + 4a = 0 → 4a = 20 → a = 5. Substituting: x² − 2x + 1 = 0 → (x − 1)² = 0 → x = 1. Choice A (−2) is the negative of the slope of the parabola's axis of symmetry. Choice C (5) is the value of a. Choice D (9) is f(1) — the y-value at the intersection: 4(1) + 5 = 9."
  },
  {
    "id": "adv_h_012",
    "num": 24,
    "type": "func_transform",
    "domain": "advanced_math",
    "difficulty": "hard",
    "calcAgnostic": false,
    "context": "Function f is defined by f(x) = 5x − c, where c is a constant. The graph of y = f(x − 3) has a y-intercept at (0, 12).",
    "stimulus": null,
    "table": null,
    "question": "What is the value of c?",
    "choices": null,
    "answer": "-27",
    "isSPR": true,
    "explanation": "Substitute x − 3 into f: f(x − 3) = 5(x − 3) − c = 5x − 15 − c. The y-intercept occurs at x = 0: −15 − c = 12 → c = −27. The common trap is treating f(x − 3) as f(x) − 3 (a vertical shift), which gives f(0) − 3 = 12 → c = −15. That's wrong because f(x − 3) is a horizontal shift: substitute x − 3 into the function's argument. Valid entries: -27."
  },
  {
    "id": "adv_h_013",
    "num": 25,
    "type": "exponent_props",
    "domain": "advanced_math",
    "difficulty": "hard",
    "calcAgnostic": true,
    "context": null,
    "stimulus": null,
    "table": null,
    "question": "The expression \\(\\dfrac{x^{5/2}}{x^{1/4}}\\) is equivalent to \\(x^k\\). What is the value of k?",
    "choices": null,
    "answer": "9/4",
    "isSPR": true,
    "explanation": "Subtract exponents when dividing same-base expressions: \\(k = \\frac{5}{2} - \\frac{1}{4} = \\frac{10}{4} - \\frac{1}{4} = \\frac{9}{4}\\). Valid entries: 9/4 or 2.25."
  },
  {
    "id": "adv_h_014",
    "num": 26,
    "type": "radical_equation",
    "domain": "advanced_math",
    "difficulty": "hard",
    "calcAgnostic": false,
    "context": "\\(\\sqrt{2x + 1} = x - 1\\)",
    "stimulus": null,
    "table": null,
    "question": "Which of the following represents the solution set of the given equation?",
    "choices": {
      "A": "{4}",
      "B": "{0}",
      "C": "{0, 4}",
      "D": "{} (no solution)"
    },
    "answer": "A",
    "isSPR": false,
    "explanation": "Square both sides: 2x + 1 = (x − 1)² = x² − 2x + 1. Rearrange: x² − 4x = 0 → x(x − 4) = 0 → x = 0 or x = 4. Check x = 0 in the original: √1 = 1 but x − 1 = −1. Since 1 ≠ −1, x = 0 is extraneous (the square root is non-negative, so it cannot equal −1). Check x = 4: √9 = 3 and 4 − 1 = 3 ✓. Solution set: {4}. Choice B gives only the extraneous root. Choice C includes the extraneous root without checking. Choice D incorrectly concludes no solution exists."
  },
  {
    "id": "adv_h_015",
    "num": 27,
    "type": "vertex_min_max",
    "domain": "advanced_math",
    "difficulty": "hard",
    "calcAgnostic": true,
    "context": "f(x) = −4x² + 20x − 3",
    "stimulus": null,
    "table": null,
    "question": "At what value of x does f reach its maximum?",
    "choices": null,
    "answer": "5/2",
    "isSPR": true,
    "explanation": "Since the leading coefficient is negative (a = −4), the parabola opens downward and the vertex is a maximum. The x-coordinate of the vertex: x = −b/(2a) = −20/(2 · (−4)) = −20/(−8) = 5/2. Valid entries: 5/2 or 2.5."
  },
  {
    "id": "adv_h_016",
    "num": 28,
    "type": "polynomial_zeros",
    "domain": "advanced_math",
    "difficulty": "hard",
    "calcAgnostic": true,
    "context": "A polynomial p(x) = x³ + bx² + cx + d has zeros at x = −1, x = 2, and x = 5.",
    "stimulus": null,
    "table": null,
    "question": "What is the value of d?",
    "choices": null,
    "answer": "10",
    "isSPR": true,
    "explanation": "Since −1, 2, and 5 are zeros, p(x) = (x + 1)(x − 2)(x − 5). The constant term d = p(0) = (0 + 1)(0 − 2)(0 − 5) = (1)(−2)(−5) = 10. Alternatively, expand: (x + 1)(x − 2) = x² − x − 2, then (x² − x − 2)(x − 5) = x³ − 6x² + 3x + 10, so d = 10. A common trap is computing the product of the zeros directly as (−1)(2)(5) = −10, forgetting the sign change from the factored form (x + 1)(x − 2)(x − 5) where each factor contributes the negative of its zero. Valid entry: 10."
  }
]

VALIDATION
Count: 28 | Easy: 8 | Medium: 12 | Hard: 8 | SPR: 8 | Dups: none

IDs used (all Advanced Math runs so far — paste into Run 11 prompt):
adv_e_001, adv_e_002, adv_e_003, adv_e_004, adv_e_005, adv_e_006, adv_e_007, adv_e_008,
adv_e_009, adv_e_010, adv_e_011, adv_e_012, adv_e_013, adv_e_014, adv_e_015, adv_e_016,
adv_m_001, adv_m_002, adv_m_003, adv_m_004, adv_m_005, adv_m_006, adv_m_007, adv_m_008,
adv_m_009, adv_m_010, adv_m_011, adv_m_012,
adv_m_013, adv_m_014, adv_m_015, adv_m_016, adv_m_017, adv_m_018, adv_m_019, adv_m_020,
adv_m_021, adv_m_022, adv_m_023, adv_m_024,
adv_h_001, adv_h_002, adv_h_003, adv_h_004, adv_h_005, adv_h_006, adv_h_007, adv_h_008,
adv_h_009, adv_h_010, adv_h_011, adv_h_012, adv_h_013, adv_h_014, adv_h_015, adv_h_016
